chrisapp/__init__.py
chrisapp/base.py
chrisapp-2.5.3.dist-info/LICENSE
chrisapp-2.5.3.dist-info/METADATA
chrisapp-2.5.3.dist-info/WHEEL
chrisapp-2.5.3.dist-info/top_level.txt
chrisapp-2.5.3.dist-info/RECORD
