Metadata-Version: 2.1
Name: chrisapp
Version: 2.5.3
Summary: Superclass for Chris plugin apps
Home-page: https://github.com/FNNDSC/chrisapp
Author: FNNDSC
Author-email: dev@babymri.org
License: MIT
Platform: UNKNOWN
Requires-Python: >=3.6
Requires-Dist: importlib-metadata ; python_version < "3.8"
